slurmster/__init__.py
slurmster/cancel.py
slurmster/cli.py
slurmster/connection.py
slurmster/core.py
slurmster/env_setup.py
slurmster/fetch.py
slurmster/gui_server.py
slurmster/monitor.py
slurmster/registry.py
slurmster/remote_utils.py
slurmster/run_status.py
slurmster/status_sync.py
slurmster/submission.py
slurmster/utils.py
slurmster/static/app.js
slurmster/static/dashboard.html
slurmster-0.2.26.dist-info/licenses/LICENSE
slurmster-0.2.26.dist-info/METADATA
slurmster-0.2.26.dist-info/WHEEL
slurmster-0.2.26.dist-info/entry_points.txt
slurmster-0.2.26.dist-info/top_level.txt
slurmster-0.2.26.dist-info/RECORD
