Metadata-Version: 2.4
Name: slurmster
Version: 0.2.26
Summary: Minimal Slurm experiment runner with persistent SSH, YAML configs, and log streaming
Requires-Python: >=3.8
License-File: LICENSE
Requires-Dist: paramiko>=3.3.0
Requires-Dist: PyYAML>=6.0
Requires-Dist: fastapi>=0.111.0
Requires-Dist: uvicorn[standard]>=0.29.0
Dynamic: license-file
